django_rest_api-0.1.5.dist-info/DESCRIPTION.rst
django_rest_api-0.1.5.dist-info/METADATA
django_rest_api-0.1.5.dist-info/metadata.json
django_rest_api-0.1.5.dist-info/RECORD
django_rest_api-0.1.5.dist-info/top_level.txt
django_rest_api-0.1.5.dist-info/WHEEL
rest_api/API.py
rest_api/auth.py
rest_api/decorators.py
rest_api/errors.py
rest_api/register.py
rest_api/__init__.py
