Metadata-Version: 1.1
Name: django-rest-api
Version: 0.1.5
Summary: Django REST API
Home-page: https://github.com/skies-io/django-rest-api
Author: Skies
Author-email: aurelien.maigret@skies.io
License: MIT
Keywords: django rest api
Platform: UNKNOWN
Classifier: Development Status :: 5 - Production/Stable
Classifier: Intended Audience :: Developers
Classifier: Topic :: Software Development :: Build Tools
Classifier: License :: OSI Approved :: MIT License
Classifier: Programming Language :: Python :: 3
Classifier: Programming Language :: Python :: 3.2
Classifier: Programming Language :: Python :: 3.3
Classifier: Programming Language :: Python :: 3.4
